.editorconfig
.flake8
.gitignore
.readthedocs.yaml
CHANGELOG.md
Dockerfile
MANIFEST.in
Makefile
README.md
docker-tox
local-tox
pyproject.toml
requirements-dev.txt
requirements-test.txt
setup.cfg
setup.py
tox.ini
.github/workflows/test.yml
amitools/__init__.py
amitools.egg-info/PKG-INFO
amitools.egg-info/SOURCES.txt
amitools.egg-info/dependency_links.txt
amitools.egg-info/entry_points.txt
amitools.egg-info/not-zip-safe
amitools.egg-info/requires.txt
amitools.egg-info/top_level.txt
amitools/binfmt/BinFmt.py
amitools/binfmt/BinImage.py
amitools/binfmt/Disassemble.py
amitools/binfmt/Dumper.py
amitools/binfmt/Relocate.py
amitools/binfmt/__init__.py
amitools/binfmt/elf/BinFmtELF.py
amitools/binfmt/elf/DwarfDebugLine.py
amitools/binfmt/elf/ELF.py
amitools/binfmt/elf/ELFDumper.py
amitools/binfmt/elf/ELFFile.py
amitools/binfmt/elf/ELFReader.py
amitools/binfmt/elf/__init__.py
amitools/binfmt/hunk/BinFmtHunk.py
amitools/binfmt/hunk/Hunk.py
amitools/binfmt/hunk/HunkBlockFile.py
amitools/binfmt/hunk/HunkDebug.py
amitools/binfmt/hunk/HunkDisassembler.py
amitools/binfmt/hunk/HunkLoadSegFile.py
amitools/binfmt/hunk/HunkReader.py
amitools/binfmt/hunk/HunkRelocate.py
amitools/binfmt/hunk/HunkShow.py
amitools/binfmt/hunk/__init__.py
amitools/data/fd/bsdsocket_lib.fd
amitools/data/fd/dos_lib.fd
amitools/data/fd/exec_lib.fd
amitools/data/fd/graphics_lib.fd
amitools/data/fd/icon_lib.fd
amitools/data/fd/iffparse_lib.fd
amitools/data/fd/intuition_lib.fd
amitools/data/fd/locale_lib.fd
amitools/data/fd/mathffp_lib.fd
amitools/data/fd/mathieeedoubbas_lib.fd
amitools/data/fd/mathieeedoubtrans_lib.fd
amitools/data/fd/mathieeesingbas_lib.fd
amitools/data/fd/mathieeesingtrans_lib.fd
amitools/data/fd/mathtrans_lib.fd
amitools/data/fd/testnix_lib.fd
amitools/data/fd/testsc_lib.fd
amitools/data/fd/timer_lib.fd
amitools/data/fd/utility_lib.fd
amitools/data/fd/vamostest_lib.fd
amitools/data/fd/vamostestdev_lib.fd
amitools/data/splitdata/README
amitools/data/splitdata/cd32_ext.dat
amitools/data/splitdata/cd32_fmv.dat
amitools/data/splitdata/cdtv_ext.dat
amitools/data/splitdata/exec44b4.dat
amitools/data/splitdata/ks31.dat
amitools/data/splitdata/ks33.dat
amitools/data/splitdata/ks34.dat
amitools/data/splitdata/ks36.dat
