Metadata-Version: 2.4
Name: amitools
Version: 0.8.1
Summary: A package to support development with classic Amiga m68k systems
Author-email: Christian Vogelgsang <chris@vogelgsang.org>
License-Expression: GPL-2.0-or-later
Keywords: AmigaOS,vamos
Classifier: Development Status :: 4 - Beta
Classifier: Intended Audience :: Developers
Classifier: Programming Language :: Python
Classifier: Topic :: System :: Emulators
Requires-Python: >=3.8
Provides-Extra: vamos
Requires-Dist: machine68k==0.3.0; extra == "vamos"
